gnps-0.1.3.dist-info/METADATA
gnps-0.1.3.dist-info/WHEEL
gnps-0.1.3.dist-info/entry_points.txt
gnps/__init__.py
gnps/__main__.py
gnps/_version.py
gnps/cell.py
gnps/cli.py
gnps/cli_transform.py
gnps/parser/__init__.py
gnps/parser/ast/__init__.py
gnps/parser/ast/boolean_expression.py
gnps/parser/ast/expression.py
gnps/parser/ast/value/__init__.py
gnps/parser/ast/value/array_value.py
gnps/parser/ast/value/base_value.py
gnps/parser/ast/value/float_value.py
gnps/parser/ast/value/math_functions.py
gnps/parser/ast/value/numerical_value.py
gnps/parser/ast/variable.py
gnps/parser/parser.py
gnps/rule.py
gnps/system.py
gnps/transformers/__init__.py
gnps/transformers/base_transformer.py
gnps/transformers/python_transformer.py
gnps-0.1.3.dist-info/RECORD
