Metadata-Version: 2.1
Name: gnps
Version: 0.1.3
Summary: Generalized Numerical P Systems simulator package
Author-Email: Sergey Verlan <dont-spam-me@no.spam>
License: MIT
Classifier: Programming Language :: Python :: 3
Classifier: License :: OSI Approved :: MIT License
Classifier: Operating System :: OS Independent
Classifier: Development Status :: 4 - Beta
Requires-Python: >=3.10
Requires-Dist: lark~=1.1
Requires-Dist: PyYAML~=6.0
